deride/__init__.py
deride/__main__.py
deride/includes.py
deride/templates/class.cpp.j2
deride/templates/class.h.j2
deride/templates/functions.cpp.j2
deride/templates/functions.h.j2
deride/templates/mock_cpp.cpp.j2
deride/templates/mock_cpp.h.j2
deride/templates/namespace.cpp.j2
deride/templates/namespace.h.j2
deride-0.4.dist-info/LICENSE
deride-0.4.dist-info/METADATA
deride-0.4.dist-info/WHEEL
deride-0.4.dist-info/entry_points.txt
deride-0.4.dist-info/top_level.txt
deride-0.4.dist-info/RECORD
