Metadata-Version: 2.1
Name: deride
Version: 0.4
Summary: A generator of mock classes for C/C++ unit testing
Home-page: https://gitlab.com/mardy/deride
Author: Alberto Mardegan
Author-email: info@mardy.it
Classifier: Development Status :: 4 - Beta
Classifier: Environment :: Console
Classifier: Framework :: Pytest
Classifier: Intended Audience :: Developers
Classifier: License :: OSI Approved :: MIT License
Classifier: Programming Language :: C
Classifier: Programming Language :: C++
Classifier: Programming Language :: Python :: 3
Classifier: Topic :: Software Development
Classifier: Topic :: Software Development :: Code Generators
Classifier: Topic :: Software Development :: Testing :: Unit
Classifier: Topic :: Utilities
License-File: LICENSE
Requires-Dist: Jinja2
Requires-Dist: clang
